Workbook

Sheet Cost Breakdown
B1: Costs & Profit numbers | C1: Notes
A2: Average Order Value | B2: 100 | C2: Dec/20 average
A4: Blended COGS
A5: COST OF GOODS (Average across SKU's) | B5: 5 | C5: =B5/$B$2 -> 0.05
A6: PAYMENT PROCESSING FEES | B6: 1.59 | C6: =B6/$B$2 -> 0.0159
A7: SHIPPING COSTS (Adjust for Free Shipping Offers) | B7: 2.32 | C7: =B7/$B$2 -> 0.0232
A8: FULLFILLMENT COST PER UNIT | B8: 2.4 | C8: =B8/$B$2 -> 0.024
A9: Discount - £ OFF | B9: 10 | C9: =B9/$B$2 -> 0.1
A10: Discount - % OFF (Enter as "XX%") | B10: 0.1 | C10: =B10 -> 0.1
A11: Incl. Free Gft cost | B11: 0 | C11: =B11/$B$2 -> 0
A13: TOTAL COSTS OF PRODUCT & TO FULFILL | B13: =B5+B6+B7+B8+B9+B11+(B10*B2) -> 31.31 | C13: =B13/$B$2 -> 0.3131
A15: Net Profit | B15: =B2-B13 -> 68.69
A16: Profit Percentage | B16: =B15/B2*1 -> 0.6869
A17: Break Even ROAS (Return on ad spend) | B17: =1/B16 -> 1.455816

Sheet ROAS, CPA, Profit
A1: Ad Spend per month | B1: 1000 | C1: 1000 | D1: 1000 | E1: 1000 | F1: 1000 | G1: 1000 | H1: 1000
A2: Revenue from Ads | B2: =B12*B11 -> 1455.816 | C2: =C12*C11 -> 2000 | D2: =D12*D11 -> 2500 | E2: =E12*E11 -> 3000 | F2: =F12*F11 -> 3500 | G2: =G12*G11 -> 4000 | H2: =H12*H11 -> 5000
A3: Cost Of Goods | B3: =B2*'Cost Breakdown'!$C$5 -> 72.790799 | C3: =C2*'Cost Breakdown'!$C$5 -> 100 | D3: =D2*'Cost Breakdown'!$C$5 -> 125 | E3: =E2*'Cost Breakdown'!$C$5 -> 150 | F3: =F2*'Cost Breakdown'!$C$5 -> 175 | G3: =G2*'Cost Breakdown'!$C$5 -> 200 | H3: =H2*'Cost Breakdown'!$C$5 -> 250
A4: Gross Profit | B4: =B2-B3 -> 1383.0252 | C4: =C2-C3 -> 1900 | D4: =D2-D3 -> 2375 | E4: =E2-E3 -> 2850 | F4: =F2-F3 -> 3325 | G4: =G2-G3 -> 3800 | H4: =H2-H3 -> 4750
A5: Payment Processing Fees | B5: =B17*'Cost Breakdown'!$B$6 -> 23.147474 | C5: =C17*'Cost Breakdown'!$B$6 -> 31.8 | D5: =D17*'Cost Breakdown'!$B$6 -> 39.75 | E5: =E17*'Cost Breakdown'!$B$6 -> 47.7 | F5: =F17*'Cost Breakdown'!$B$6 -> 55.65 | G5: =G17*'Cost Breakdown'!$B$6 -> 63.6 | H5: =H17*'Cost Breakdown'!$B$6 -> 79.5
A6: Shipping Fees | B6: ='Cost Breakdown'!$B$7*B17 -> 33.774931 | C6: ='Cost Breakdown'!$B$7*C17 -> 46.4 | D6: ='Cost Breakdown'!$B$7*D17 -> 58 | E6: ='Cost Breakdown'!$B$7*E17 -> 69.6 | F6: ='Cost Breakdown'!$B$7*F17 -> 81.2 | G6: ='Cost Breakdown'!$B$7*G17 -> 92.8 | H6: ='Cost Breakdown'!$B$7*H17 -> 116
A7: Fullfillment Fees | B7: ='Cost Breakdown'!B8*B17 -> 34.939584 | C7: ='Cost Breakdown'!B8*C17 -> 48 | D7: ='Cost Breakdown'!B8*D17 -> 60 | E7: ='Cost Breakdown'!B8*E17 -> 72 | F7: ='Cost Breakdown'!B8*F17 -> 84 | G7: ='Cost Breakdown'!B8*G17 -> 96 | H7: ='Cost Breakdown'!B8*H17 -> 120
A8: Discount (£ Off) | B8: ='Cost Breakdown'!$B$9*B17 -> 145.5816 | C8: ='Cost Breakdown'!$B$9*C17 -> 200 | D8: ='Cost Breakdown'!$B$9*D17 -> 250 | E8: ='Cost Breakdown'!$B$9*E17 -> 300 | F8: ='Cost Breakdown'!$B$9*F17 -> 350 | G8: ='Cost Breakdown'!$B$9*G17 -> 400 | H8: ='Cost Breakdown'!$B$9*H17 -> 500
A9: Discount (% Off) | B9: =B2*'Cost Breakdown'!$C$10 -> 145.5816 | C9: =C2*'Cost Breakdown'!$C$10 -> 200 | D9: =D2*'Cost Breakdown'!$C$10 -> 250 | E9: =E2*'Cost Breakdown'!$C$10 -> 300 | F9: =F2*'Cost Breakdown'!$C$10 -> 350 | G9: =G2*'Cost Breakdown'!$C$10 -> 400 | H9: =H2*'Cost Breakdown'!$C$10 -> 500
A10: Free Gift cost (£) | B10: ='Cost Breakdown'!$B$11*B17 -> 0 | C10: ='Cost Breakdown'!$B$11*C17 -> 0 | D10: ='Cost Breakdown'!$B$11*D17 -> 0 | E10: ='Cost Breakdown'!$B$11*E17 -> 0 | F10: ='Cost Breakdown'!$B$11*F17 -> 0 | G10: ='Cost Breakdown'!$B$11*G17 -> 0 | H10: ='Cost Breakdown'!$B$11*H17 -> 0
A11: Ad Spend | B11: =B1 -> 1000 | C11: =C1 -> 1000 | D11: =D1 -> 1000 | E11: =E1 -> 1000 | F11: =F1 -> 1000 | G11: =G1 -> 1000 | H11: =H1 -> 1000
A12: ROAS | B12: ='Cost Breakdown'!B17 -> 1.455816 | C12: 2 | D12: 2.5 | E12: 3 | F12: 3.5 | G12: 4 | H12: 5
A14: Profit | B14: =B4-B5-B6-B7-B8-B9-B10-B11 -> 0 | C14: =C4-C5-C6-C7-C8-C9-C10-C11 -> 373.8 | D14: =D4-D5-D6-D7-D8-D9-D10-D11 -> 717.25 | E14: =E4-E5-E6-E7-E8-E9-E10-E11 -> 1060.7 | F14: =F4-F5-F6-F7-F8-F9-F10-F11 -> 1404.15 | G14: =G4-G5-G6-G7-G8-G9-G10-G11 -> 1747.6 | H14: =H4-H5-H6-H7-H8-H9-H10-H11 -> 2434.5
A16: AOV | B16: ='Cost Breakdown'!$B$2 -> 100 | C16: ='Cost Breakdown'!$B$2 -> 100 | D16: ='Cost Breakdown'!$B$2 -> 100 | E16: ='Cost Breakdown'!$B$2 -> 100 | F16: ='Cost Breakdown'!$B$2 -> 100 | G16: ='Cost Breakdown'!$B$2 -> 100 | H16: ='Cost Breakdown'!$B$2 -> 100
A17: Transactions | B17: =B2/B16 -> 14.55816 | C17: =C2/C16 -> 20 | D17: =D2/D16 -> 25 | E17: =E2/E16 -> 30 | F17: =F2/F16 -> 35 | G17: =G2/G16 -> 40 | H17: =H2/H16 -> 50
A19: CPA Target | B19: =B16/B12 -> 68.69 | C19: =C16/C12 -> 50 | D19: =D16/D12 -> 40 | E19: =E16/E12 -> 33.333333 | F19: =F16/F12 -> 28.571429 | G19: =G16/G12 -> 25 | H19: =H16/H12 -> 20
